turbo_http/__init__.py
turbo_http/__version__.py
turbo_http/_turbo.py
turbo_http/turbo_intruder/request.py
turbo_http/turbo_intruder/request.txt
turbo_http/turbo_intruder/turbo.jar
turbo_http-0.1.2.dist-info/METADATA
turbo_http-0.1.2.dist-info/WHEEL
turbo_http-0.1.2.dist-info/top_level.txt
turbo_http-0.1.2.dist-info/RECORD
